vidcutter/__init__.py
vidcutter/__main__.py
vidcutter/about.py
vidcutter/changelog.py
vidcutter/mediainfo.py
vidcutter/mediastream.py
vidcutter/resources.py
vidcutter/settings.py
vidcutter/updater.py
vidcutter/videoconsole.py
vidcutter/videocutter.py
vidcutter/videolist.py
vidcutter/videoslider.py
vidcutter/videosliderwidget.py
vidcutter/videostyle.py
vidcutter/libs/__init__.py
vidcutter/libs/config.py
vidcutter/libs/ffmetadata.py
vidcutter/libs/graphicseffects.py
vidcutter/libs/iso639.py
vidcutter/libs/mpv.cp39-win_amd64.pyd
vidcutter/libs/mpvwidget.py
vidcutter/libs/munch.py
vidcutter/libs/notifications.py
vidcutter/libs/singleapplication.py
vidcutter/libs/taskbarprogress.py
vidcutter/libs/videoservice.py
vidcutter/libs/widgets.py
vidcutter-6.0.5.1.dist-info/LICENSE
vidcutter-6.0.5.1.dist-info/METADATA
vidcutter-6.0.5.1.dist-info/WHEEL
vidcutter-6.0.5.1.dist-info/entry_points.txt
vidcutter-6.0.5.1.dist-info/top_level.txt
vidcutter-6.0.5.1.dist-info/RECORD
